{
  "data": {
    "article": {},
    "attachments": {
      "media_keys": [
        "13_2056191114890092544"
      ],
      "media_source_tweet_id": [
        "2056191125669482658"
      ]
    },
    "author_id": "2053366838248259584",
    "conversation_id": "2058681652948488529",
    "created_at": "2026-05-24T22:48:49.000Z",
    "edit_controls": {
      "editable_until": "2026-05-24T23:48:49.000Z",
      "edits_remaining": 5,
      "is_edit_eligible": false
    },
    "edit_history_tweet_ids": [
      "2058681652948488529"
    ],
    "entities": {
      "mentions": [
        {
          "end": 14,
          "id": "1317365789213794305",
          "start": 3,
          "username": "glockk1tty"
        }
      ],
      "urls": [
        {
          "display_url": "pic.x.com/JQ1XchiXL2",
          "end": 39,
          "expanded_url": "https://x.com/glockk1tty/status/2056191125669482658/video/1",
          "media_key": "13_2056191114890092544",
          "start": 16,
          "url": "https://t.co/JQ1XchiXL2"
        }
      ]
    },
    "geo": {},
    "id": "2058681652948488529",
    "lang": "zxx",
    "note_tweet": {
      "entities": {}
    },
    "possibly_sensitive": false,
    "public_metrics": {
      "bookmark_count": 0,
      "impression_count": 0,
      "like_count": 0,
      "quote_count": 0,
      "reply_count": 0,
      "retweet_count": 12
    },
    "referenced_tweets": [
      {
        "id": "2056191125669482658",
        "type": "retweeted"
      }
    ],
    "reply_settings": "everyone",
    "text": "RT @glockk1tty: https://t.co/JQ1XchiXL2"
  },
  "errors": [
    {
      "detail": "Could not find tweet with edit_history_tweet_ids: [2058681652948488529].",
      "parameter": "edit_history_tweet_ids",
      "resource_id": "2058681652948488529",
      "resource_type": "tweet",
      "title": "Not Found Error",
      "type": "https://api.twitter.com/2/problems/resource-not-found",
      "value": "2058681652948488529"
    }
  ],
  "includes": {
    "media": [
      {
        "duration_ms": 4888,
        "height": 480,
        "media_key": "13_2056191114890092544",
        "preview_image_url": "https://pbs.twimg.com/amplify_video_thumb/2056191114890092544/img/WDVhO8S2otI2yuGP.jpg",
        "public_metrics": {
          "view_count": 1503
        },
        "type": "video",
        "variants": [
          {
            "bit_rate": 256000,
            "content_type": "video/mp4",
            "url": "https://video.twimg.com/amplify_video/2056191114890092544/vid/avc1/360x270/-ELB0-O3y2ksTN37.mp4"
          },
          {
            "bit_rate": 832000,
            "content_type": "video/mp4",
            "url": "https://video.twimg.com/amplify_video/2056191114890092544/vid/avc1/480x360/9QK4AVPY1hYDckWF.mp4"
          },
          {
            "bit_rate": 2176000,
            "content_type": "video/mp4",
            "url": "https://video.twimg.com/amplify_video/2056191114890092544/vid/avc1/640x480/eHhYv2UWvJZdins6.mp4"
          },
          {
            "content_type": "application/x-mpegURL",
            "url": "https://video.twimg.com/amplify_video/2056191114890092544/pl/1fgw24ioD8cMp8al.m3u8"
          }
        ],
        "width": 640
      }
    ],
    "tweets": [
      {
        "article": {},
        "attachments": {
          "media_keys": [
            "13_2056191114890092544"
          ]
        },
        "author_id": "1317365789213794305",
        "conversation_id": "2056191125669482658",
        "created_at": "2026-05-18T01:52:21.000Z",
        "edit_controls": {
          "editable_until": "2026-05-18T02:52:21.000Z",
          "edits_remaining": 5,
          "is_edit_eligible": true
        },
        "edit_history_tweet_ids": [
          "2056191125669482658"
        ],
        "entities": {
          "urls": [
            {
              "display_url": "pic.x.com/JQ1XchiXL2",
              "end": 23,
              "expanded_url": "https://x.com/glockk1tty/status/2056191125669482658/video/1",
              "media_key": "13_2056191114890092544",
              "start": 0,
              "url": "https://t.co/JQ1XchiXL2"
            }
          ]
        },
        "geo": {},
        "id": "2056191125669482658",
        "lang": "zxx",
        "note_tweet": {
          "entities": {}
        },
        "possibly_sensitive": false,
        "public_metrics": {
          "bookmark_count": 44,
          "impression_count": 6843,
          "like_count": 352,
          "quote_count": 2,
          "reply_count": 1,
          "retweet_count": 12
        },
        "reply_settings": "everyone",
        "text": "https://t.co/JQ1XchiXL2"
      }
    ],
    "users": [
      {
        "created_at": "2026-05-10T06:50:59.000Z",
        "description": "因为爱存在\n| 已成年| BD | OVERDOSE | BISEXUAL | 语言是 中韩英|\n男生查成分互fo | 女生都fo | 不可接受小粉红 ！！！|(没回就私信我）",
        "id": "2053366838248259584",
        "name": "酸性✝️",
        "pinned_tweet_id": "2057485786535313415",
        "profile_image_url": "https://pbs.twimg.com/profile_images/2057427639531638786/4bR3vvpl_normal.jpg",
        "protected": false,
        "public_metrics": {
          "followers_count": 167,
          "following_count": 163,
          "like_count": 118,
          "listed_count": 0,
          "media_count": 4,
          "tweet_count": 235
        },
        "username": "Cassie2meqwq",
        "verified": false
      },
      {
        "created_at": "2020-10-17T07:24:23.000Z",
        "description": "ig @glockk1tty",
        "entities": {
          "description": {
            "mentions": [
              {
                "end": 14,
                "start": 3,
                "username": "glockk1tty"
              }
            ]
          },
          "url": {
            "urls": [
              {
                "display_url": "open.spotify.com/artist/5VhJoMC…",
                "end": 23,
                "expanded_url": "https://open.spotify.com/artist/5VhJoMCPj40nB9yfMAb99i?si=hJPYu8O8QY-u9Pgffe4CKg",
                "start": 0,
                "url": "https://t.co/JGQBaUIydc"
              }
            ]
          }
        },
        "id": "1317365789213794305",
        "location": "The Pit",
        "name": "GLOCK ✞",
        "pinned_tweet_id": "2055147114972229749",
        "profile_image_url": "https://pbs.twimg.com/profile_images/2058094963695460352/NL0LosfE_normal.jpg",
        "protected": false,
        "public_metrics": {
          "followers_count": 70500,
          "following_count": 17,
          "like_count": 34407,
          "listed_count": 75,
          "media_count": 457,
          "tweet_count": 3147
        },
        "url": "https://t.co/JGQBaUIydc",
        "username": "glockk1tty",
        "verified": true
      }
    ]
  }
}